gaesynkit
