Metadata-Version: 1.0
Name: gaesynkit
Version: 1.0.0a2
Summary: Google App Engine Datastore/Local Storage Synchronization Framework
Home-page: http://code.google.com/p/gaesynkit
Author: Tobias Rodaebel
Author-email: tobias.rodaebel@googlemail.com
License: Apache License 2.0
Keywords: google app engine gae javascript datastore
Platform: UNKNOWN
Classifier: Development Status :: 3 - Alpha
Classifier: Environment :: Web Environment
Classifier: Intended Audience :: Developers
Classifier: License :: OSI Approved :: Apache Software License
Classifier: Natural Language :: English
Classifier: Operating System :: OS Independent
Classifier: Programming Language :: JavaScript
Classifier: Programming Language :: Python
Classifier: Topic :: Internet :: WWW/HTTP
Classifier: Topic :: Internet :: WWW/HTTP :: WSGI :: Server
